metromobilite/__init__.py
metromobilite/metromobilite.py
metromobilite/metromobilite_exception.py
tests/__init__.py
tests/test_metromobilite.py
metromobilite-0.2.1.dist-info/LICENSE
metromobilite-0.2.1.dist-info/METADATA
metromobilite-0.2.1.dist-info/WHEEL
metromobilite-0.2.1.dist-info/top_level.txt
metromobilite-0.2.1.dist-info/RECORD
