Metadata-Version: 2.1
Name: metromobilite
Version: 0.2.1
Summary: Python library for metromobilite API
Home-page: https://github.com/PierreBerger/metromobilite
Author: PierreBerger
License: MIT
Platform: UNKNOWN
License-File: LICENSE
